{
  "lastUpdate": 1771701005123,
  "heartbeat": "GOOD",
  "uptime": 3.774147028,
  "wallets": {
    "yield": {
      "address": "2xQ4KC...HswK",
      "balance": "0.2972",
      "pnl": {
        "realized": 8.133385164142,
        "unrealized": -2.671607002959,
        "total": 5.461778161183,
        "winRate": 0
      }
    },
    "sniper": {
      "address": "4DkcEp...bPzp",
      "balance": "0.0161",
      "pnl": null
    }
  },
  "totalBalance": "0.3133",
  "mode": "DUAL_CORE",
  "logs": [
    {
      "timestamp": "2026-02-21T13:53:21.854Z",
      "message": "TRADE_EXECUTION: AVF9F4C4j8b1Kh4BmNHqybDaHgnZpJ7W7yLvL7hUpump (submitted)"
    },
    {
      "timestamp": "2026-02-21T13:53:53.677Z",
      "message": "TRADE_EXECUTION: AVF9F4C4j8b1Kh4BmNHqybDaHgnZpJ7W7yLvL7hUpump (submitted)"
    },
    {
      "timestamp": "2026-02-21T15:49:09.381Z",
      "message": "TRADE_EXECUTION: So11111111111111111111111111111111111111112 (submitted)"
    },
    {
      "timestamp": "2026-02-21T15:54:28.579Z",
      "message": "TRADE_EXECUTION: So11111111111111111111111111111111111111112 (submitted)"
    },
    {
      "timestamp": "2026-02-21T16:04:39.507Z",
      "message": "TRADE_EXECUTION: NV2RYH954cTJ3ckFUpvfqaQXU4ARqqDH3562nFSpump (submitted)"
    },
    {
      "timestamp": "2026-02-21T16:09:56.872Z",
      "message": "TRADE_EXECUTION: AVF9F4C4j8b1Kh4BmNHqybDaHgnZpJ7W7yLvL7hUpump (submitted)"
    },
    {
      "timestamp": "2026-02-21T16:10:30.555Z",
      "message": "TRADE_EXECUTION: AVF9F4C4j8b1Kh4BmNHqybDaHgnZpJ7W7yLvL7hUpump (submitted)"
    },
    {
      "timestamp": "2026-02-21T18:05:37.965Z",
      "message": "TRADE_EXECUTION: So11111111111111111111111111111111111111112 (submitted)"
    },
    {
      "timestamp": "2026-02-21T18:10:58.621Z",
      "message": "TRADE_EXECUTION: So11111111111111111111111111111111111111112 (submitted)"
    },
    {
      "timestamp": "2026-02-21T18:20:47.806Z",
      "message": "TRADE_EXECUTION: NV2RYH954cTJ3ckFUpvfqaQXU4ARqqDH3562nFSpump (submitted)"
    }
  ],
  "thought": "Trade executions submitted successfully, balance holds at 0.3133 SOL; next logical move: evaluate market trends for optimal re-entry point.",
  "chartData": {
    "labels": [
      "19:13",
      "19:40",
      "20:09",
      "20:35",
      "21:00",
      "21:25",
      "21:56",
      "22:21",
      "22:50",
      "23:17",
      "23:42",
      "00:10",
      "00:38",
      "01:03",
      "01:29",
      "01:54",
      "02:20",
      "02:49",
      "03:14",
      "03:40",
      "04:10",
      "04:36",
      "05:01",
      "05:26",
      "05:52",
      "06:20",
      "06:47",
      "07:13",
      "07:39",
      "08:05",
      "08:30",
      "09:00",
      "09:30",
      "09:56",
      "10:21",
      "10:47",
      "11:12",
      "11:40",
      "12:07",
      "12:32",
      "13:10",
      "13:55",
      "14:40",
      "15:21",
      "16:07",
      "16:50",
      "17:34",
      "18:19",
      "19:00"
    ],
    "data": [
      0.323500624,
      0.33859314,
      0.30838314,
      0.30838314,
      0.30838314,
      0.30838314,
      0.33938718500000004,
      0.309177192,
      0.309177192,
      0.309177192,
      0.309177192,
      0.341728674,
      0.294581815,
      0.294581815,
      0.294581815,
      0.294581815,
      0.34137188900000004,
      0.296335672,
      0.296335672,
      0.296335672,
      0.296335672,
      0.345186264,
      0.255053121,
      0.255053121,
      0.255053121,
      0.255053121,
      0.284861956,
      0.251421629,
      0.251421629,
      0.251421629,
      0.251421629,
      0.251421629,
      0.27381335100000004,
      0.27381335100000004,
      0.27381335100000004,
      0.27381335100000004,
      0.27381335100000004,
      0.28366039200000004,
      0.28366039200000004,
      0.28366039200000004,
      0.28366039200000004,
      0.305988153,
      0.305988153,
      0.305988154,
      0.331398032,
      0.301284467,
      0.301284467,
      0.328350745,
      0.313312873
    ]
  },
  "strategy": {
    "name": "Momentum_V2: Sentinel",
    "winRate": "0%",
    "realizedPnL": 8.133385164142,
    "unrealizedPnL": -2.671607002959,
    "totalPnL": 5.461778161183,
    "activePositions": "Active"
  },
  "positions": [
    {
      "symbol": "UNTRACKED_NV2R",
      "address": "NV2RYH954cTJ3ckFUpvfqaQXU4ARqqDH3562nFSpump",
      "pnl": 0,
      "age": "1.0h"
    },
    {
      "symbol": "Punch-SOL",
      "address": "NV2RYH954cTJ3ckFUpvfqaQXU4ARqqDH3562nFSpump",
      "pnl": 0,
      "age": "0.8h"
    }
  ]
}