{
  "lastUpdate": 1771408804614,
  "heartbeat": "GOOD",
  "uptime": 3.14266601,
  "wallets": {
    "yield": {
      "address": "2xQ4KC...HswK",
      "balance": "0.2509",
      "pnl": {
        "realized": 9.887841676371002,
        "unrealized": -3.222206045008,
        "total": 6.665635631363003,
        "winRate": 0
      }
    },
    "sniper": {
      "address": "4DkcEp...bPzp",
      "balance": "0.0161",
      "pnl": null
    }
  },
  "totalBalance": "0.2670",
  "mode": "DUAL_CORE",
  "logs": [
    {
      "timestamp": "2026-02-18T09:59:58.347Z",
      "message": "DISCOVERY_METEORA: So11111111111111111111111111111111111111112 (candidate)"
    },
    {
      "timestamp": "2026-02-18T09:59:58.355Z",
      "message": "DISCOVERY_METEORA: So11111111111111111111111111111111111111112 (candidate)"
    },
    {
      "timestamp": "2026-02-18T09:59:58.367Z",
      "message": "DISCOVERY_METEORA: So11111111111111111111111111111111111111112 (candidate)"
    },
    {
      "timestamp": "2026-02-18T09:59:58.372Z",
      "message": "DISCOVERY_METEORA: cbbtcf3aa214zXHbiAZQwf4122FBYbraNdFqgw4iMij (candidate)"
    },
    {
      "timestamp": "2026-02-18T09:59:58.378Z",
      "message": "DISCOVERY_METEORA: pumpCmXqMfrsAkQ5r49WcJnRayYRqmXz6ae8H7H9Dfn (candidate)"
    },
    {
      "timestamp": "2026-02-18T09:59:58.396Z",
      "message": "DISCOVERY_METEORA: HaUXAdAWWUkb2WTmh8z1TdaEmZkYjnQnmC6tHUdTAHvi (candidate)"
    },
    {
      "timestamp": "2026-02-18T09:59:58.431Z",
      "message": "DISCOVERY_METEORA: NV2RYH954cTJ3ckFUpvfqaQXU4ARqqDH3562nFSpump (candidate)"
    },
    {
      "timestamp": "2026-02-18T09:59:58.448Z",
      "message": "DISCOVERY_METEORA: pumpCmXqMfrsAkQ5r49WcJnRayYRqmXz6ae8H7H9Dfn (candidate)"
    },
    {
      "timestamp": "2026-02-18T09:59:58.454Z",
      "message": "DISCOVERY_METEORA: A7bdiYdS5GjqGFtxf17ppRHtDKPkkRqbKtR27dxvQXaS (candidate)"
    },
    {
      "timestamp": "2026-02-18T09:59:58.461Z",
      "message": "DISCOVERY_METEORA: soKqZS9pASwBNS46G388nhK7XVtPaTyReffXEd3zora (candidate)"
    }
  ],
  "thought": "Analyzing recent discoveries of potential trading candidates, with a balance of 0.2670 SOL, strategic evaluation and potential acquisition of cbbtcf3aa214zXHbiAZQwf4122FBYbraNdFqgw4iMij or pumpCmXqMfrsAkQ5r49WcJnRayYRqmXz6ae8H7H9Dfn is the optimal next move.",
  "chartData": {
    "labels": [
      "10:00",
      "10:30",
      "11:01",
      "11:31",
      "12:01",
      "12:32",
      "13:02",
      "13:33",
      "14:03",
      "14:33",
      "15:04",
      "15:34",
      "16:05",
      "16:35",
      "17:04",
      "17:35",
      "18:05",
      "18:36",
      "19:20",
      "19:55",
      "20:25",
      "20:56",
      "21:27",
      "21:57",
      "22:27",
      "22:57",
      "23:28",
      "23:59",
      "00:29",
      "00:59",
      "01:29",
      "02:00",
      "02:30",
      "03:00",
      "03:30",
      "04:00",
      "04:30",
      "05:00",
      "05:30",
      "06:00",
      "06:30",
      "07:00",
      "07:30",
      "08:01",
      "08:32",
      "09:01",
      "09:32"
    ],
    "data": [
      0.359288166,
      0.359288166,
      0.359288166,
      0.359288166,
      0.359288166,
      0.359288166,
      0.359288166,
      0.359288166,
      0.359288166,
      0.359288166,
      0.359288166,
      0.359288166,
      0.359288166,
      0.359288166,
      0.359288166,
      0.359288166,
      0.359288166,
      0.359288166,
      0.299104554,
      0.299104554,
      0.299104554,
      0.299104554,
      0.299104554,
      0.299104554,
      0.299104554,
      0.299104554,
      0.299104554,
      0.299104554,
      0.299104554,
      0.299104554,
      0.299104554,
      0.299104554,
      0.299104554,
      0.299104554,
      0.299104554,
      0.299104554,
      0.299104554,
      0.299104554,
      0.299104554,
      0.299104554,
      0.299104554,
      0.299104554,
      0.299104554,
      0.299104554,
      0.299104554,
      0.299104554,
      0.267020474
    ]
  },
  "strategy": {
    "name": "Momentum_V2: Sentinel",
    "winRate": "0%",
    "realizedPnL": 9.887841676371002,
    "unrealizedPnL": -3.222206045008,
    "totalPnL": 6.665635631363003,
    "activePositions": "Active"
  },
  "positions": [
    {
      "symbol": "MAYA-SOL",
      "address": "EtL967sgMgeDDSUrNhtQrbhe4T92idzqf4VuA6H7uGfQ",
      "pnl": 0,
      "age": "15.4h"
    },
    {
      "symbol": "KIMCHI-SOL",
      "address": "HaUXAdAWWUkb2WTmh8z1TdaEmZkYjnQnmC6tHUdTAHvi",
      "pnl": 0,
      "age": "0.7h"
    }
  ]
}