{
  "lastUpdate": 1771872004129,
  "heartbeat": "GOOD",
  "uptime": 2.264816516,
  "wallets": {
    "yield": {
      "address": "2xQ4KC...HswK",
      "balance": "0.2622",
      "pnl": {
        "realized": 9.633607319321998,
        "unrealized": -1.71971876807,
        "total": 7.913888551251999,
        "winRate": 0
      }
    },
    "sniper": {
      "address": "4DkcEp...bPzp",
      "balance": "0.0161",
      "pnl": null
    }
  },
  "totalBalance": "0.2783",
  "mode": "DUAL_CORE",
  "logs": [
    {
      "timestamp": "2026-02-23T15:15:49.141Z",
      "message": "TRADE_EXECUTION: 8NFNhyWJF8dTWRxLN4Tq4SXkVaPHYncQm5vJ49hpump (submitted)"
    },
    {
      "timestamp": "2026-02-23T15:15:50.751Z",
      "message": "TRADE_EXECUTION: 8NFNhyWJF8dTWRxLN4Tq4SXkVaPHYncQm5vJ49hpump (submitted)"
    },
    {
      "timestamp": "2026-02-23T15:16:26.128Z",
      "message": "TRADE_EXECUTION: 3LmH79u9NH5AjYxEBAyJtWkCZD875zCqPzvhELaUpump (submitted)"
    },
    {
      "timestamp": "2026-02-23T15:16:26.640Z",
      "message": "TRADE_EXECUTION: 3LmH79u9NH5AjYxEBAyJtWkCZD875zCqPzvhELaUpump (submitted)"
    },
    {
      "timestamp": "2026-02-23T17:16:48.160Z",
      "message": "TRADE_EXECUTION: So11111111111111111111111111111111111111112 (submitted)"
    },
    {
      "timestamp": "2026-02-23T17:16:48.419Z",
      "message": "TRADE_EXECUTION: So11111111111111111111111111111111111111112 (submitted)"
    },
    {
      "timestamp": "2026-02-23T17:17:27.029Z",
      "message": "TRADE_EXECUTION: 9N4Lwoqy2dgDxLNt5LGNSwutvftzGHVcgpNzecVobXby (submitted)"
    },
    {
      "timestamp": "2026-02-23T17:17:27.114Z",
      "message": "TRADE_EXECUTION: 9N4Lwoqy2dgDxLNt5LGNSwutvftzGHVcgpNzecVobXby (submitted)"
    },
    {
      "timestamp": "2026-02-23T17:17:59.643Z",
      "message": "TRADE_EXECUTION: BKQucpTXB2d67jSNXMznSTj2iNLVtyga9JW86QoWpump (submitted)"
    },
    {
      "timestamp": "2026-02-23T17:18:00.215Z",
      "message": "TRADE_EXECUTION: BKQucpTXB2d67jSNXMznSTj2iNLVtyga9JW86QoWpump (submitted)"
    }
  ],
  "thought": "Balance holding at 0.2783 SOL with multiple trade submissions; assess recent trade outcomes and recalibrate strategy for optimal gains.",
  "chartData": {
    "labels": [
      "18:40",
      "19:20",
      "20:00",
      "20:40",
      "21:20",
      "22:00",
      "22:23",
      "22:44",
      "23:07",
      "23:32",
      "23:57",
      "00:20",
      "00:43",
      "01:20",
      "02:00",
      "02:40",
      "03:20",
      "03:55",
      "04:20",
      "04:45",
      "05:10",
      "05:40",
      "06:10",
      "06:50",
      "07:30",
      "08:10",
      "08:40",
      "09:09",
      "09:30",
      "09:54",
      "10:20",
      "10:45",
      "11:16",
      "11:56",
      "12:37",
      "13:18",
      "13:58",
      "14:39",
      "15:14",
      "15:39",
      "16:05",
      "16:30",
      "16:56",
      "17:21",
      "17:46",
      "18:10",
      "18:37"
    ],
    "data": [
      0.344288633,
      0.344288633,
      0.344288633,
      0.344288633,
      0.344288633,
      0.344288633,
      0.344288633,
      0.344288633,
      0.344288633,
      0.344288633,
      0.344288633,
      0.344288633,
      0.344288633,
      0.344288633,
      0.344288633,
      0.344288633,
      0.344288633,
      0.344288633,
      0.344288633,
      0.344288633,
      0.344288633,
      0.344288633,
      0.344288633,
      0.344288633,
      0.344288633,
      0.344288633,
      0.344288633,
      0.344288633,
      0.344288633,
      0.344288633,
      0.344288633,
      0.344288633,
      0.344288633,
      0.344288633,
      0.344288633,
      0.344288633,
      0.344288633,
      0.32918363300000003,
      0.32918363300000003,
      0.264618122,
      0.264618125,
      0.264618125,
      0.264618125,
      0.27832453,
      0.27832453,
      0.27832453,
      0.27832453
    ]
  },
  "strategy": {
    "name": "Momentum_V2: Sentinel",
    "winRate": "0%",
    "realizedPnL": 9.633607319321998,
    "unrealizedPnL": -1.71971876807,
    "totalPnL": 7.913888551251999,
    "activePositions": "Active"
  },
  "positions": [
    {
      "symbol": "Lovecoin-SOL",
      "address": "9N4Lwoqy2dgDxLNt5LGNSwutvftzGHVcgpNzecVobXby",
      "pnl": 0,
      "age": "1.4h"
    },
    {
      "symbol": "UNTRACKED_BKQu",
      "address": "BKQucpTXB2d67jSNXMznSTj2iNLVtyga9JW86QoWpump",
      "pnl": 0,
      "age": "1.4h"
    }
  ]
}