{
  "heartbeat": "RUNNING",
  "uptime": 35676,
  "health": "GOOD",
  "pnl": 0,
  "logs": [
    {
      "time": "2026-02-08T15:58:12.740Z",
      "level": "INFO",
      "msg": "Detected signal: xAI ($xAI)"
    },
    {
      "time": "2026-02-08T15:58:18.143Z",
      "level": "INFO",
      "msg": "Detected signal: The Crypto Dog ($DOG)"
    },
    {
      "time": "2026-02-08T15:58:18.601Z",
      "level": "INFO",
      "msg": "DISCOVERY_METEORA: So11111111111111111111111111111111111111112"
    },
    {
      "time": "2026-02-08T15:58:18.775Z",
      "level": "INFO",
      "msg": "DISCOVERY_METEORA: cbbtcf3aa214zXHbiAZQwf4122FBYbraNdFqgw4iMij"
    },
    {
      "time": "2026-02-08T15:58:18.896Z",
      "level": "INFO",
      "msg": "DISCOVERY_METEORA: 8Jx8AAHj86wbQgUTjGuj6GTTL5Ps3cqxKRTvpaJApump"
    },
    {
      "time": "2026-02-08T15:58:18.976Z",
      "level": "INFO",
      "msg": "DISCOVERY_METEORA: 98sMhvDwXj1RQi5c5Mndm3vPe9cBqPrbLaufMXFNMh5g"
    },
    {
      "time": "2026-02-08T15:58:19.058Z",
      "level": "INFO",
      "msg": "DISCOVERY_METEORA: So11111111111111111111111111111111111111112"
    },
    {
      "time": "2026-02-08T15:58:19.120Z",
      "level": "INFO",
      "msg": "DISCOVERY_METEORA: So11111111111111111111111111111111111111112"
    },
    {
      "time": "2026-02-08T15:58:19.216Z",
      "level": "INFO",
      "msg": "DISCOVERY_METEORA: pumpCmXqMfrsAkQ5r49WcJnRayYRqmXz6ae8H7H9Dfn"
    },
    {
      "time": "2026-02-08T15:58:19.298Z",
      "level": "INFO",
      "msg": "DISCOVERY_METEORA: 2k8yZaJjf61unHriuqdmvbxe7CUhEYML5kVJDbcotKjU"
    },
    {
      "time": "2026-02-08T15:58:19.363Z",
      "level": "INFO",
      "msg": "DISCOVERY_METEORA: jupSoLaHXQiZZTSfEWMTRRgpnyFm8f6sZdosWBjx93v"
    },
    {
      "time": "2026-02-08T15:58:19.432Z",
      "level": "INFO",
      "msg": "DISCOVERY_METEORA: Cm6fNnMk7NfzStP9CZpsQA2v3jjzbcYGAxdJySmHpump"
    },
    {
      "time": "2026-02-08T15:58:25.695Z",
      "level": "INFO",
      "msg": "Detected signal: I’m Not Fucking Leaving ($Leaving)"
    },
    {
      "time": "2026-02-08T15:58:28.571Z",
      "level": "INFO",
      "msg": "Detected signal: FARTCOIN ($FRT)"
    },
    {
      "time": "2026-02-08T15:58:36.875Z",
      "level": "INFO",
      "msg": "Detected signal: GOKU ($GOKU)"
    },
    {
      "time": "2026-02-08T15:58:39.469Z",
      "level": "INFO",
      "msg": "Detected signal: Pippin ($pippin)"
    },
    {
      "time": "2026-02-08T15:58:50.417Z",
      "level": "INFO",
      "msg": "Detected signal: GRIMES_V2 ($GrimesAI)"
    },
    {
      "time": "2026-02-08T15:58:59.811Z",
      "level": "INFO",
      "msg": "Detected signal: SpaceX ($SpaceX)"
    },
    {
      "time": "2026-02-08T15:59:02.482Z",
      "level": "INFO",
      "msg": "Detected signal: Comedian ($Ban)"
    },
    {
      "time": "2026-02-08T15:59:07.371Z",
      "level": "INFO",
      "msg": "Detected signal: soliloquy_cat REAL NAME ($Slinks)"
    },
    {
      "time": "2026-02-08T15:59:14.819Z",
      "level": "INFO",
      "msg": "DISCOVERY_METEORA: So11111111111111111111111111111111111111112"
    },
    {
      "time": "2026-02-08T15:59:14.950Z",
      "level": "INFO",
      "msg": "DISCOVERY_METEORA: cbbtcf3aa214zXHbiAZQwf4122FBYbraNdFqgw4iMij"
    },
    {
      "time": "2026-02-08T15:59:15.034Z",
      "level": "INFO",
      "msg": "DISCOVERY_METEORA: 8Jx8AAHj86wbQgUTjGuj6GTTL5Ps3cqxKRTvpaJApump"
    },
    {
      "time": "2026-02-08T15:59:15.136Z",
      "level": "INFO",
      "msg": "DISCOVERY_METEORA: 98sMhvDwXj1RQi5c5Mndm3vPe9cBqPrbLaufMXFNMh5g"
    },
    {
      "time": "2026-02-08T15:59:15.222Z",
      "level": "INFO",
      "msg": "DISCOVERY_METEORA: So11111111111111111111111111111111111111112"
    },
    {
      "time": "2026-02-08T15:59:15.295Z",
      "level": "INFO",
      "msg": "DISCOVERY_METEORA: So11111111111111111111111111111111111111112"
    },
    {
      "time": "2026-02-08T15:59:15.369Z",
      "level": "INFO",
      "msg": "DISCOVERY_METEORA: pumpCmXqMfrsAkQ5r49WcJnRayYRqmXz6ae8H7H9Dfn"
    },
    {
      "time": "2026-02-08T15:59:15.436Z",
      "level": "INFO",
      "msg": "DISCOVERY_METEORA: 2k8yZaJjf61unHriuqdmvbxe7CUhEYML5kVJDbcotKjU"
    },
    {
      "time": "2026-02-08T15:59:15.529Z",
      "level": "INFO",
      "msg": "DISCOVERY_METEORA: jupSoLaHXQiZZTSfEWMTRRgpnyFm8f6sZdosWBjx93v"
    },
    {
      "time": "2026-02-08T15:59:15.614Z",
      "level": "INFO",
      "msg": "DISCOVERY_METEORA: Cm6fNnMk7NfzStP9CZpsQA2v3jjzbcYGAxdJySmHpump"
    },
    {
      "time": "2026-02-08T15:59:18.079Z",
      "level": "INFO",
      "msg": "Detected signal: xAI ($xAI)"
    },
    {
      "time": "2026-02-08T15:59:20.884Z",
      "level": "INFO",
      "msg": "Detected signal: GRIMES_V2 ($GrimesAI)"
    },
    {
      "time": "2026-02-08T15:59:23.284Z",
      "level": "INFO",
      "msg": "Detected signal: The White Swan ($WhiteSwan)"
    },
    {
      "time": "2026-02-08T15:59:28.437Z",
      "level": "INFO",
      "msg": "Detected signal: GRIMES_V2 ($GrimesAI)"
    },
    {
      "time": "2026-02-08T15:59:33.842Z",
      "level": "INFO",
      "msg": "Detected signal: OG AT 25K? ($DICAPRIO)"
    },
    {
      "time": "2026-02-08T15:59:43.327Z",
      "level": "INFO",
      "msg": "Detected signal: SpaceX ($SpaceX)"
    },
    {
      "time": "2026-02-08T15:59:46.028Z",
      "level": "INFO",
      "msg": "Detected signal: The One ($ NEO)"
    },
    {
      "time": "2026-02-08T15:59:48.723Z",
      "level": "INFO",
      "msg": "Detected signal: Just a chill guy ($CHILLGUY)"
    },
    {
      "time": "2026-02-08T15:59:51.541Z",
      "level": "INFO",
      "msg": "Detected signal: NYANMARU COIN ($NYAN)"
    },
    {
      "time": "2026-02-08T15:59:54.140Z",
      "level": "INFO",
      "msg": "Detected signal: OG AT 25K? ($DICAPRIO)"
    },
    {
      "time": "2026-02-08T15:59:56.541Z",
      "level": "INFO",
      "msg": "DISCOVERY_METEORA: So11111111111111111111111111111111111111112"
    },
    {
      "time": "2026-02-08T15:59:56.728Z",
      "level": "INFO",
      "msg": "DISCOVERY_METEORA: cbbtcf3aa214zXHbiAZQwf4122FBYbraNdFqgw4iMij"
    },
    {
      "time": "2026-02-08T15:59:56.916Z",
      "level": "INFO",
      "msg": "DISCOVERY_METEORA: 8Jx8AAHj86wbQgUTjGuj6GTTL5Ps3cqxKRTvpaJApump"
    },
    {
      "time": "2026-02-08T15:59:56.990Z",
      "level": "INFO",
      "msg": "DISCOVERY_METEORA: 98sMhvDwXj1RQi5c5Mndm3vPe9cBqPrbLaufMXFNMh5g"
    },
    {
      "time": "2026-02-08T15:59:57.058Z",
      "level": "INFO",
      "msg": "DISCOVERY_METEORA: So11111111111111111111111111111111111111112"
    },
    {
      "time": "2026-02-08T15:59:57.124Z",
      "level": "INFO",
      "msg": "DISCOVERY_METEORA: So11111111111111111111111111111111111111112"
    },
    {
      "time": "2026-02-08T15:59:57.218Z",
      "level": "INFO",
      "msg": "DISCOVERY_METEORA: pumpCmXqMfrsAkQ5r49WcJnRayYRqmXz6ae8H7H9Dfn"
    },
    {
      "time": "2026-02-08T15:59:57.320Z",
      "level": "INFO",
      "msg": "DISCOVERY_METEORA: 2k8yZaJjf61unHriuqdmvbxe7CUhEYML5kVJDbcotKjU"
    },
    {
      "time": "2026-02-08T15:59:57.411Z",
      "level": "INFO",
      "msg": "DISCOVERY_METEORA: jupSoLaHXQiZZTSfEWMTRRgpnyFm8f6sZdosWBjx93v"
    },
    {
      "time": "2026-02-08T15:59:57.478Z",
      "level": "INFO",
      "msg": "DISCOVERY_METEORA: Cm6fNnMk7NfzStP9CZpsQA2v3jjzbcYGAxdJySmHpump"
    }
  ],
  "positions": [],
  "thought": "Analyzing market microstructure for next opportunity..."
}