{
  "lastUpdate": 1771096204161,
  "heartbeat": "GOOD",
  "uptime": 2.624893987,
  "wallets": {
    "yield": {
      "address": "2xQ4KC...HswK",
      "balance": "0.3890",
      "pnl": {
        "realized": 8.275546013767002,
        "unrealized": -0.007842303658,
        "total": 8.267703710109,
        "winRate": 0
      }
    },
    "sniper": {
      "address": "4DkcEp...bPzp",
      "balance": "0.2000",
      "pnl": null
    }
  },
  "totalBalance": "0.5890",
  "mode": "DUAL_CORE",
  "logs": [
    {
      "timestamp": "2026-02-14T19:10:00.272Z",
      "message": "DISCOVERY_METEORA: So11111111111111111111111111111111111111112 (candidate)"
    },
    {
      "timestamp": "2026-02-14T19:10:00.275Z",
      "message": "DISCOVERY_METEORA: So11111111111111111111111111111111111111112 (candidate)"
    },
    {
      "timestamp": "2026-02-14T19:10:00.280Z",
      "message": "DISCOVERY_METEORA: cbbtcf3aa214zXHbiAZQwf4122FBYbraNdFqgw4iMij (candidate)"
    },
    {
      "timestamp": "2026-02-14T19:10:00.282Z",
      "message": "DISCOVERY_METEORA: So11111111111111111111111111111111111111112 (candidate)"
    },
    {
      "timestamp": "2026-02-14T19:10:00.286Z",
      "message": "DISCOVERY_METEORA: pumpCmXqMfrsAkQ5r49WcJnRayYRqmXz6ae8H7H9Dfn (candidate)"
    },
    {
      "timestamp": "2026-02-14T19:10:00.288Z",
      "message": "DISCOVERY_METEORA: A7bdiYdS5GjqGFtxf17ppRHtDKPkkRqbKtR27dxvQXaS (candidate)"
    },
    {
      "timestamp": "2026-02-14T19:10:00.291Z",
      "message": "DISCOVERY_METEORA: DezXAZ8z7PnrnRJjz3wXBoRgixCa6xjnB7YaB1pPB263 (candidate)"
    },
    {
      "timestamp": "2026-02-14T19:10:00.293Z",
      "message": "DISCOVERY_METEORA: 98sMhvDwXj1RQi5c5Mndm3vPe9cBqPrbLaufMXFNMh5g (candidate)"
    },
    {
      "timestamp": "2026-02-14T19:10:00.296Z",
      "message": "DISCOVERY_METEORA: Cm6fNnMk7NfzStP9CZpsQA2v3jjzbcYGAxdJySmHpump (candidate)"
    },
    {
      "timestamp": "2026-02-14T19:10:00.298Z",
      "message": "DISCOVERY_METEORA: pumpCmXqMfrsAkQ5r49WcJnRayYRqmXz6ae8H7H9Dfn (candidate)"
    }
  ],
  "thought": "Balance stable at 0.5890 SOL; multiple Meteora candidates identified, with pumpCmXqMfrsAkQ5r49WcJnRayYRqmXz6ae8H7H9Dfn as potential target—initiate further analysis before engagement.",
  "chartData": {
    "labels": [
      "19:10",
      "19:58",
      "20:44",
      "21:21",
      "21:50",
      "22:19",
      "22:39",
      "23:26",
      "00:11",
      "01:00",
      "01:42",
      "02:10",
      "02:38",
      "03:08",
      "03:34",
      "04:04",
      "04:30",
      "05:00",
      "05:30",
      "05:56",
      "06:26",
      "06:52",
      "07:22",
      "07:50",
      "08:18",
      "08:47",
      "09:14",
      "09:43",
      "10:10",
      "10:40",
      "11:10",
      "11:36",
      "12:06",
      "12:32",
      "13:01",
      "13:30",
      "13:57",
      "14:28",
      "14:54",
      "15:24",
      "15:50",
      "16:20",
      "16:49",
      "17:16",
      "17:45",
      "18:11",
      "18:41",
      "19:10"
    ],
    "data": [
      0.619025476,
      0.6337281450000001,
      0.6270716540000001,
      0.622042541,
      0.626528803,
      0.611144855,
      0.611144855,
      0.625559313,
      0.625535688,
      0.6076314140000001,
      0.617098557,
      0.606108086,
      0.576108052,
      0.605823252,
      0.590553133,
      0.590084547,
      0.589116558,
      0.603551876,
      0.6035532880000001,
      0.603553292,
      0.587906436,
      0.6274866100000001,
      0.556854269,
      0.617095692,
      0.616855805,
      0.586323527,
      0.6158333730000001,
      0.6004634440000001,
      0.5849538240000001,
      0.584804334,
      0.599443238,
      0.584338239,
      0.598689912,
      0.598124871,
      0.583246166,
      0.597995,
      0.582507375,
      0.5820535010000001,
      0.596487872,
      0.581126665,
      0.595921524,
      0.5799911289999999,
      0.5947791849999999,
      0.607249951,
      0.6168927660000001,
      0.5764215340000001,
      0.559590476,
      0.589009083
    ]
  },
  "strategy": {
    "name": "Momentum_V2: Sentinel",
    "winRate": "0%",
    "realizedPnL": 8.275546013767002,
    "unrealizedPnL": -0.007842303658,
    "totalPnL": 8.267703710109,
    "activePositions": "Active"
  },
  "positions": [
    {
      "symbol": "PUMP-SOL",
      "address": "pumpCmXqMfrsAkQ5r49WcJnRayYRqmXz6ae8H7H9Dfn",
      "pnl": 0,
      "age": "0.3h"
    },
    {
      "symbol": "ZEC-SOL",
      "address": "A7bdiYdS5GjqGFtxf17ppRHtDKPkkRqbKtR27dxvQXaS",
      "pnl": 0,
      "age": "0.2h"
    }
  ]
}