{
  "lastUpdate": 1771058404486,
  "heartbeat": "GOOD",
  "uptime": 2.780845564,
  "wallets": {
    "yield": {
      "address": "2xQ4KC...HswK",
      "balance": "0.3863",
      "pnl": {
        "realized": 8.195982828958996,
        "unrealized": 0.009618588438,
        "total": 8.205601417394998,
        "winRate": 0
      }
    },
    "sniper": {
      "address": "4DkcEp...bPzp",
      "balance": "0.2000",
      "pnl": null
    }
  },
  "totalBalance": "0.5863",
  "mode": "DUAL_CORE",
  "logs": [
    {
      "timestamp": "2026-02-14T08:39:44.754Z",
      "message": "DISCOVERY_METEORA: So11111111111111111111111111111111111111112 (candidate)"
    },
    {
      "timestamp": "2026-02-14T08:39:44.766Z",
      "message": "DISCOVERY_METEORA: So11111111111111111111111111111111111111112 (candidate)"
    },
    {
      "timestamp": "2026-02-14T08:39:44.773Z",
      "message": "DISCOVERY_METEORA: cbbtcf3aa214zXHbiAZQwf4122FBYbraNdFqgw4iMij (candidate)"
    },
    {
      "timestamp": "2026-02-14T08:39:44.787Z",
      "message": "DISCOVERY_METEORA: So11111111111111111111111111111111111111112 (candidate)"
    },
    {
      "timestamp": "2026-02-14T08:39:44.792Z",
      "message": "DISCOVERY_METEORA: pumpCmXqMfrsAkQ5r49WcJnRayYRqmXz6ae8H7H9Dfn (candidate)"
    },
    {
      "timestamp": "2026-02-14T08:39:44.799Z",
      "message": "DISCOVERY_METEORA: A7bdiYdS5GjqGFtxf17ppRHtDKPkkRqbKtR27dxvQXaS (candidate)"
    },
    {
      "timestamp": "2026-02-14T08:39:44.803Z",
      "message": "DISCOVERY_METEORA: JUPyiwrYJFskUPiHa7hkeR8VUtAeFoSYbKedZNsDvCN (candidate)"
    },
    {
      "timestamp": "2026-02-14T08:39:44.806Z",
      "message": "DISCOVERY_METEORA: 98sMhvDwXj1RQi5c5Mndm3vPe9cBqPrbLaufMXFNMh5g (candidate)"
    },
    {
      "timestamp": "2026-02-14T08:39:44.811Z",
      "message": "DISCOVERY_METEORA: cbbtcf3aa214zXHbiAZQwf4122FBYbraNdFqgw4iMij (candidate)"
    },
    {
      "timestamp": "2026-02-14T08:39:44.815Z",
      "message": "DISCOVERY_METEORA: a3W4qutoEJA4232T2gwZUfgYJTetr96pU4SJMwppump (candidate)"
    }
  ],
  "thought": "Balance at 0.5863 SOL; recent discoveries indicate multiple candidate tokens, with \"pumpCmXqMfrsAkQ5r49WcJnRayYRqmXz6ae8H7H9Dfn\" as a potential target for further analysis and strategic engagement.",
  "chartData": {
    "labels": [
      "08:50",
      "10:30",
      "12:10",
      "13:50",
      "15:25",
      "16:00",
      "16:32",
      "17:06",
      "17:40",
      "18:10",
      "18:30",
      "18:51",
      "19:16",
      "19:50",
      "20:24",
      "20:55",
      "21:21",
      "21:42",
      "22:03",
      "22:20",
      "22:35",
      "23:04",
      "23:40",
      "00:11",
      "00:46",
      "01:20",
      "01:47",
      "02:07",
      "02:27",
      "02:48",
      "03:08",
      "03:28",
      "03:48",
      "04:09",
      "04:30",
      "04:49",
      "05:10",
      "05:30",
      "05:50",
      "06:10",
      "06:30",
      "06:50",
      "07:10",
      "07:30",
      "07:50",
      "08:10",
      "08:30"
    ],
    "data": [
      0.238129222,
      0.238129222,
      0.238129222,
      0.238129222,
      0.239571812,
      0.23405681700000003,
      0.635844878,
      0.630673898,
      0.636862174,
      0.634502739,
      0.634502739,
      0.609172379,
      0.619025476,
      0.6337281450000001,
      0.629317093,
      0.6270716540000001,
      0.622042541,
      0.6265288019999999,
      0.626528803,
      0.611144855,
      0.611144855,
      0.610708393,
      0.625559313,
      0.625535688,
      0.62292477,
      0.602580519,
      0.621414135,
      0.606108086,
      0.5761080510000001,
      0.576108052,
      0.605823252,
      0.590553133,
      0.590553133,
      0.590084547,
      0.589116558,
      0.589116558,
      0.603551876,
      0.6035532880000001,
      0.603553291,
      0.5879064350000001,
      0.612550682,
      0.6274866100000001,
      0.556854269,
      0.556854269,
      0.617095692,
      0.6168558040000001,
      0.616855805
    ]
  },
  "strategy": {
    "name": "Momentum_V2: Sentinel",
    "winRate": "0%",
    "realizedPnL": 8.195982828958996,
    "unrealizedPnL": 0.009618588438,
    "totalPnL": 8.205601417394998,
    "activePositions": "Active"
  },
  "positions": [
    {
      "symbol": "JUP-SOL",
      "address": "JUPyiwrYJFskUPiHa7hkeR8VUtAeFoSYbKedZNsDvCN",
      "pnl": 0,
      "age": "0.1h"
    },
    {
      "symbol": "HYPE-SOL",
      "address": "98sMhvDwXj1RQi5c5Mndm3vPe9cBqPrbLaufMXFNMh5g",
      "pnl": 0,
      "age": "0.1h"
    }
  ]
}