{
  "lastUpdate": 1771392003236,
  "heartbeat": "GOOD",
  "uptime": 2.175712953,
  "wallets": {
    "yield": {
      "address": "2xQ4KC...HswK",
      "balance": "0.2830",
      "pnl": {
        "realized": 9.887841676371002,
        "unrealized": -2.633518420186,
        "total": 7.254323256184001,
        "winRate": 0
      }
    },
    "sniper": {
      "address": "4DkcEp...bPzp",
      "balance": "0.0161",
      "pnl": null
    }
  },
  "totalBalance": "0.2991",
  "mode": "DUAL_CORE",
  "logs": [
    {
      "timestamp": "2026-02-18T05:19:41.228Z",
      "message": "DISCOVERY_METEORA: So11111111111111111111111111111111111111112 (candidate)"
    },
    {
      "timestamp": "2026-02-18T05:19:41.231Z",
      "message": "DISCOVERY_METEORA: So11111111111111111111111111111111111111112 (candidate)"
    },
    {
      "timestamp": "2026-02-18T05:19:41.235Z",
      "message": "DISCOVERY_METEORA: So11111111111111111111111111111111111111112 (candidate)"
    },
    {
      "timestamp": "2026-02-18T05:19:41.239Z",
      "message": "DISCOVERY_METEORA: cbbtcf3aa214zXHbiAZQwf4122FBYbraNdFqgw4iMij (candidate)"
    },
    {
      "timestamp": "2026-02-18T05:19:41.243Z",
      "message": "DISCOVERY_METEORA: HaUXAdAWWUkb2WTmh8z1TdaEmZkYjnQnmC6tHUdTAHvi (candidate)"
    },
    {
      "timestamp": "2026-02-18T05:19:41.246Z",
      "message": "DISCOVERY_METEORA: pumpCmXqMfrsAkQ5r49WcJnRayYRqmXz6ae8H7H9Dfn (candidate)"
    },
    {
      "timestamp": "2026-02-18T05:19:41.250Z",
      "message": "DISCOVERY_METEORA: NV2RYH954cTJ3ckFUpvfqaQXU4ARqqDH3562nFSpump (candidate)"
    },
    {
      "timestamp": "2026-02-18T05:19:41.253Z",
      "message": "DISCOVERY_METEORA: pumpCmXqMfrsAkQ5r49WcJnRayYRqmXz6ae8H7H9Dfn (candidate)"
    },
    {
      "timestamp": "2026-02-18T05:19:41.256Z",
      "message": "DISCOVERY_METEORA: soKqZS9pASwBNS46G388nhK7XVtPaTyReffXEd3zora (candidate)"
    },
    {
      "timestamp": "2026-02-18T05:19:41.259Z",
      "message": "DISCOVERY_METEORA: A7bdiYdS5GjqGFtxf17ppRHtDKPkkRqbKtR27dxvQXaS (candidate)"
    }
  ],
  "thought": "Current balance is 0.2991 SOL; discovered potential candidates including So11111111111111111111111111111111111111112, cbbtcf3aa214zXHbiAZQwf4122FBYbraNdFqgw4iMij, and HaUXAdAWWUkb2WTmh8z1TdaEmZkYjnQnmC6tHUdTAHvi; next move: analyze candidates for optimal trade execution.",
  "chartData": {
    "labels": [
      "05:21",
      "05:51",
      "06:22",
      "06:52",
      "07:22",
      "07:52",
      "08:23",
      "08:54",
      "09:24",
      "09:54",
      "10:24",
      "10:55",
      "11:26",
      "11:56",
      "12:26",
      "12:57",
      "13:27",
      "13:58",
      "14:29",
      "14:58",
      "15:29",
      "15:59",
      "16:30",
      "17:00",
      "17:30",
      "18:00",
      "18:30",
      "19:10",
      "19:50",
      "20:20",
      "20:50",
      "21:20",
      "21:50",
      "22:20",
      "22:50",
      "23:20",
      "23:50",
      "00:20",
      "00:50",
      "01:20",
      "01:50",
      "02:21",
      "02:51",
      "03:22",
      "03:53",
      "04:22",
      "04:53"
    ],
    "data": [
      0.359288166,
      0.359288166,
      0.359288166,
      0.359288166,
      0.359288166,
      0.359288166,
      0.359288166,
      0.359288166,
      0.359288166,
      0.359288166,
      0.359288166,
      0.359288166,
      0.359288166,
      0.359288166,
      0.359288166,
      0.359288166,
      0.359288166,
      0.359288166,
      0.359288166,
      0.359288166,
      0.359288166,
      0.359288166,
      0.359288166,
      0.359288166,
      0.359288166,
      0.359288166,
      0.359288166,
      0.299104554,
      0.299104554,
      0.299104554,
      0.299104554,
      0.299104554,
      0.299104554,
      0.299104554,
      0.299104554,
      0.299104554,
      0.299104554,
      0.299104554,
      0.299104554,
      0.299104554,
      0.299104554,
      0.299104554,
      0.299104554,
      0.299104554,
      0.299104554,
      0.299104554,
      0.299104554
    ]
  },
  "strategy": {
    "name": "Momentum_V2: Sentinel",
    "winRate": "0%",
    "realizedPnL": 9.887841676371002,
    "unrealizedPnL": -2.633518420186,
    "totalPnL": 7.254323256184001,
    "activePositions": "Active"
  },
  "positions": [
    {
      "symbol": "Punch-SOL",
      "address": "NV2RYH954cTJ3ckFUpvfqaQXU4ARqqDH3562nFSpump",
      "pnl": 0,
      "age": "10.7h"
    },
    {
      "symbol": "MAYA-SOL",
      "address": "EtL967sgMgeDDSUrNhtQrbhe4T92idzqf4VuA6H7uGfQ",
      "pnl": 0,
      "age": "10.7h"
    }
  ]
}