{
  "lastUpdate": 1771505404366,
  "heartbeat": "GOOD",
  "uptime": 3.255175048,
  "wallets": {
    "yield": {
      "address": "2xQ4KC...HswK",
      "balance": "0.2655",
      "pnl": {
        "realized": 4.451874461990004,
        "unrealized": -1.903083015003,
        "total": 2.548791446987003,
        "winRate": 0
      }
    },
    "sniper": {
      "address": "4DkcEp...bPzp",
      "balance": "0.0161",
      "pnl": null
    }
  },
  "totalBalance": "0.2816",
  "mode": "DUAL_CORE",
  "logs": [
    {
      "timestamp": "2026-02-19T12:49:47.274Z",
      "message": "DISCOVERY_METEORA: So11111111111111111111111111111111111111112 (candidate)"
    },
    {
      "timestamp": "2026-02-19T12:49:47.279Z",
      "message": "DISCOVERY_METEORA: So11111111111111111111111111111111111111112 (candidate)"
    },
    {
      "timestamp": "2026-02-19T12:49:47.283Z",
      "message": "DISCOVERY_METEORA: cbbtcf3aa214zXHbiAZQwf4122FBYbraNdFqgw4iMij (candidate)"
    },
    {
      "timestamp": "2026-02-19T12:49:47.287Z",
      "message": "DISCOVERY_METEORA: So11111111111111111111111111111111111111112 (candidate)"
    },
    {
      "timestamp": "2026-02-19T12:49:47.294Z",
      "message": "DISCOVERY_METEORA: PreANxuXjsy2pvisWWMNB6YaJNzr7681wJJr2rHsfTh (candidate)"
    },
    {
      "timestamp": "2026-02-19T12:49:47.300Z",
      "message": "DISCOVERY_METEORA: PreweJYECqtQwBtpxHL171nL2K6umo692gTm7Q3rpgF (candidate)"
    },
    {
      "timestamp": "2026-02-19T12:49:47.306Z",
      "message": "DISCOVERY_METEORA: Pren1FvFX6J3E4kXhJuCiAD5aDmGEb7qJRncwA8Lkhw (candidate)"
    },
    {
      "timestamp": "2026-02-19T12:49:47.313Z",
      "message": "DISCOVERY_METEORA: 98sMhvDwXj1RQi5c5Mndm3vPe9cBqPrbLaufMXFNMh5g (candidate)"
    },
    {
      "timestamp": "2026-02-19T12:49:47.318Z",
      "message": "DISCOVERY_METEORA: AWpD39myXc7emw5M9cMCofkbo92x5FKWdGHWYpZFdoge (candidate)"
    },
    {
      "timestamp": "2026-02-19T12:49:47.322Z",
      "message": "DISCOVERY_METEORA: 98sMhvDwXj1RQi5c5Mndm3vPe9cBqPrbLaufMXFNMh5g (candidate)"
    }
  ],
  "thought": "Current Status: With a balance of 0.2816 SOL and multiple promising candidates identified, including So11111111111111111111111111111111111111112 and PreANxuXjsy2pvisWWMNB6YaJNzr7681wJJr2rHsfTh, the next logical move is to evaluate candidate viability for potential investment.",
  "chartData": {
    "labels": [
      "12:50",
      "13:20",
      "13:50",
      "14:20",
      "14:51",
      "15:21",
      "15:51",
      "16:22",
      "16:57",
      "17:23",
      "17:47",
      "18:17",
      "18:47",
      "19:18",
      "19:48",
      "20:18",
      "20:49",
      "21:19",
      "21:50",
      "22:20",
      "22:50",
      "23:20",
      "23:50",
      "00:20",
      "00:50",
      "01:20",
      "01:50",
      "02:20",
      "02:50",
      "03:20",
      "03:50",
      "04:21",
      "04:50",
      "05:21",
      "05:51",
      "06:22",
      "06:52",
      "07:22",
      "07:52",
      "08:23",
      "08:54",
      "09:25",
      "09:54",
      "10:24",
      "10:55",
      "11:25",
      "11:55",
      "12:25"
    ],
    "data": [
      0.267020474,
      0.267020474,
      0.267020474,
      0.267020474,
      0.267020474,
      0.267020474,
      0.267020474,
      0.267020474,
      0.267020474,
      0.267020474,
      0.22180267399999998,
      0.22180267399999998,
      0.22180267399999998,
      0.22180267399999998,
      0.22180267399999998,
      0.22180267399999998,
      0.22180267399999998,
      0.22180267399999998,
      0.25153107,
      0.235976611,
      0.230517323,
      0.21990718599999998,
      0.218901727,
      0.218249941,
      0.202380297,
      0.206905087,
      0.230884082,
      0.24541795100000002,
      0.260442598,
      0.22599267899999997,
      0.18218484899999998,
      0.242507317,
      0.227230484,
      0.17942077499999998,
      0.21391252700000002,
      0.17743511899999997,
      0.203423334,
      0.25262894,
      0.162296092,
      0.17779276300000002,
      0.19788742799999998,
      0.225269873,
      0.209990542,
      0.23636605700000002,
      0.29604561,
      0.285690478,
      0.297443481,
      0.28176685700000004
    ]
  },
  "strategy": {
    "name": "Momentum_V2: Sentinel",
    "winRate": "0%",
    "realizedPnL": 4.451874461990004,
    "unrealizedPnL": -1.903083015003,
    "totalPnL": 2.548791446987003,
    "activePositions": "Active"
  },
  "positions": [
    {
      "symbol": "KIMCHI-SOL",
      "address": "AWpD39myXc7emw5M9cMCofkbo92x5FKWdGHWYpZFdoge",
      "pnl": 0,
      "age": "0.3h"
    }
  ]
}